functionalytics/__init__.py
functionalytics/log_this.py
functionalytics-0.6.1.dist-info/METADATA
functionalytics-0.6.1.dist-info/WHEEL
functionalytics-0.6.1.dist-info/licenses/LICENSE
functionalytics-0.6.1.dist-info/RECORD
