Metadata-Version: 2.4
Name: functionalytics
Version: 0.6.1
Summary: Function(ality) analytics for your apps.
Project-URL: homepage, https://github.com/eliasdabbas/functionalytics
Author-email: Elias Dabbas <eliasdabbas@gmail.com>
License-File: LICENSE
Requires-Python: >=3.8
Provides-Extra: dev
Requires-Dist: mypy; extra == 'dev'
Requires-Dist: pytest; extra == 'dev'
Requires-Dist: pytest-cov; extra == 'dev'
Requires-Dist: ruff; extra == 'dev'
Requires-Dist: tox-uv; extra == 'dev'
